{
  "version": "3.4",
  "log": [
    {
      "@openzeppelin/contracts-upgradeable/access/AccessControlUpgradeable.sol:AccessControlUpgradeable": {
        "src": "@openzeppelin/contracts-upgradeable/access/AccessControlUpgradeable.sol:51",
        "inherit": [
          "@openzeppelin/contracts-upgradeable/utils/introspection/ERC165Upgradeable.sol:ERC165Upgradeable",
          "@openzeppelin/contracts/utils/introspection/IERC165.sol:IERC165",
          "@openzeppelin/contracts/access/IAccessControl.sol:IAccessControl",
          "@openzeppelin/contracts-upgradeable/utils/ContextUpgradeable.sol:ContextUpgradeable",
          "@openzeppelin/contracts-upgradeable/proxy/utils/Initializable.sol:Initializable"
        ],
        "libraries": [],
        "methods": [
          "supportsInterface(bytes4)",
          "hasRole(bytes32,address)",
          "getRoleAdmin(bytes32)",
          "grantRole(bytes32,address)",
          "revokeRole(bytes32,address)",
          "renounceRole(bytes32,address)"
        ],
        "linkReferences": [],
        "errors": [],
        "layout": {
          "storage": [],
          "types": {
            "t_mapping(t_bytes32,t_struct(RoleData)27_storage)": {
              "label": "mapping(bytes32 => struct AccessControlUpgradeable.RoleData)"
            },
            "t_bytes32": {
              "label": "bytes32"
            },
            "t_struct(RoleData)27_storage": {
              "label": "struct AccessControlUpgradeable.RoleData",
              "members": [
                {
                  "label": "hasRole",
                  "type": "t_mapping(t_address,t_bool)"
                },
                {
                  "label": "adminRole",
                  "type": "t_bytes32"
                }
              ]
            },
            "t_mapping(t_address,t_bool)": {
              "label": "mapping(address => bool)"
            },
            "t_address": {
              "label": "address"
            },
            "t_bool": {
              "label": "bool"
            },
            "t_uint64": {
              "label": "uint64"
            }
          },
          "layoutVersion": "1.2",
          "flat": false,
          "namespaces": {
            "erc7201:openzeppelin.storage.AccessControl": [
              {
                "contract": "AccessControlUpgradeable",
                "label": "_roles",
                "type": "t_mapping(t_bytes32,t_struct(RoleData)27_storage)",
                "src": "@openzeppelin/contracts-upgradeable/access/AccessControlUpgradeable.sol:62"
              }
            ],
            "erc7201:openzeppelin.storage.Initializable": [
              {
                "contract": "Initializable",
                "label": "_initialized",
                "type": "t_uint64",
                "src": "@openzeppelin/contracts-upgradeable/proxy/utils/Initializable.sol:69"
              },
              {
                "contract": "Initializable",
                "label": "_initializing",
                "type": "t_bool",
                "src": "@openzeppelin/contracts-upgradeable/proxy/utils/Initializable.sol:73"
              }
            ]
          }
        },
        "solcVersion": "0.8.22"
      },
      "@openzeppelin/contracts-upgradeable/proxy/utils/Initializable.sol:Initializable": {
        "src": "@openzeppelin/contracts-upgradeable/proxy/utils/Initializable.sol:56",
        "inherit": [],
        "libraries": [],
        "methods": [],
        "linkReferences": [],
        "errors": [],
        "layout": {
          "storage": [],
          "types": {
            "t_uint64": {
              "label": "uint64"
            },
            "t_bool": {
              "label": "bool"
            }
          },
          "layoutVersion": "1.2",
          "flat": false,
          "namespaces": {
            "erc7201:openzeppelin.storage.Initializable": [
              {
                "contract": "Initializable",
                "label": "_initialized",
                "type": "t_uint64",
                "src": "@openzeppelin/contracts-upgradeable/proxy/utils/Initializable.sol:69"
              },
              {
                "contract": "Initializable",
                "label": "_initializing",
                "type": "t_bool",
                "src": "@openzeppelin/contracts-upgradeable/proxy/utils/Initializable.sol:73"
              }
            ]
          }
        },
        "solcVersion": "0.8.22"
      },
      "@openzeppelin/contracts-upgradeable/proxy/utils/UUPSUpgradeable.sol:UUPSUpgradeable": {
        "src": "@openzeppelin/contracts-upgradeable/proxy/utils/UUPSUpgradeable.sol:20",
        "inherit": [
          "@openzeppelin/contracts/interfaces/draft-IERC1822.sol:IERC1822Proxiable",
          "@openzeppelin/contracts-upgradeable/proxy/utils/Initializable.sol:Initializable"
        ],
        "libraries": [
          "@openzeppelin/contracts/proxy/ERC1967/ERC1967Utils.sol:ERC1967Utils"
        ],
        "methods": [
          "proxiableUUID()",
          "upgradeToAndCall(address,bytes)"
        ],
        "linkReferences": [],
        "errors": [
          {
            "kind": "delegatecall",
            "src": "@openzeppelin/contracts/utils/Address.sol:97"
          }
        ],
        "layout": {
          "storage": [],
          "types": {
            "t_uint64": {
              "label": "uint64"
            },
            "t_bool": {
              "label": "bool"
            }
          },
          "layoutVersion": "1.2",
          "flat": false,
          "namespaces": {
            "erc7201:openzeppelin.storage.Initializable": [
              {
                "contract": "Initializable",
                "label": "_initialized",
                "type": "t_uint64",
                "src": "@openzeppelin/contracts-upgradeable/proxy/utils/Initializable.sol:69"
              },
              {
                "contract": "Initializable",
                "label": "_initializing",
                "type": "t_bool",
                "src": "@openzeppelin/contracts-upgradeable/proxy/utils/Initializable.sol:73"
              }
            ]
          }
        },
        "solcVersion": "0.8.22"
      },
      "@openzeppelin/contracts-upgradeable/utils/ContextUpgradeable.sol:ContextUpgradeable": {
        "src": "@openzeppelin/contracts-upgradeable/utils/ContextUpgradeable.sol:17",
        "inherit": [
          "@openzeppelin/contracts-upgradeable/proxy/utils/Initializable.sol:Initializable"
        ],
        "libraries": [],
        "methods": [],
        "linkReferences": [],
        "errors": [],
        "layout": {
          "storage": [],
          "types": {
            "t_uint64": {
              "label": "uint64"
            },
            "t_bool": {
              "label": "bool"
            }
          },
          "layoutVersion": "1.2",
          "flat": false,
          "namespaces": {
            "erc7201:openzeppelin.storage.Initializable": [
              {
                "contract": "Initializable",
                "label": "_initialized",
                "type": "t_uint64",
                "src": "@openzeppelin/contracts-upgradeable/proxy/utils/Initializable.sol:69"
              },
              {
                "contract": "Initializable",
                "label": "_initializing",
                "type": "t_bool",
                "src": "@openzeppelin/contracts-upgradeable/proxy/utils/Initializable.sol:73"
              }
            ]
          }
        },
        "solcVersion": "0.8.22"
      },
      "@openzeppelin/contracts-upgradeable/utils/PausableUpgradeable.sol:PausableUpgradeable": {
        "src": "@openzeppelin/contracts-upgradeable/utils/PausableUpgradeable.sol:18",
        "inherit": [
          "@openzeppelin/contracts-upgradeable/utils/ContextUpgradeable.sol:ContextUpgradeable",
          "@openzeppelin/contracts-upgradeable/proxy/utils/Initializable.sol:Initializable"
        ],
        "libraries": [],
        "methods": [
          "paused()"
        ],
        "linkReferences": [],
        "errors": [],
        "layout": {
          "storage": [],
          "types": {
            "t_bool": {
              "label": "bool"
            },
            "t_uint64": {
              "label": "uint64"
            }
          },
          "layoutVersion": "1.2",
          "flat": false,
          "namespaces": {
            "erc7201:openzeppelin.storage.Pausable": [
              {
                "contract": "PausableUpgradeable",
                "label": "_paused",
                "type": "t_bool",
                "src": "@openzeppelin/contracts-upgradeable/utils/PausableUpgradeable.sol:21"
              }
            ],
            "erc7201:openzeppelin.storage.Initializable": [
              {
                "contract": "Initializable",
                "label": "_initialized",
                "type": "t_uint64",
                "src": "@openzeppelin/contracts-upgradeable/proxy/utils/Initializable.sol:69"
              },
              {
                "contract": "Initializable",
                "label": "_initializing",
                "type": "t_bool",
                "src": "@openzeppelin/contracts-upgradeable/proxy/utils/Initializable.sol:73"
              }
            ]
          }
        },
        "solcVersion": "0.8.22"
      },
      "@openzeppelin/contracts-upgradeable/utils/ReentrancyGuardUpgradeable.sol:ReentrancyGuardUpgradeable": {
        "src": "@openzeppelin/contracts-upgradeable/utils/ReentrancyGuardUpgradeable.sol:26",
        "inherit": [
          "@openzeppelin/contracts-upgradeable/proxy/utils/Initializable.sol:Initializable"
        ],
        "libraries": [],
        "methods": [],
        "linkReferences": [],
        "errors": [],
        "layout": {
          "storage": [],
          "types": {
            "t_uint256": {
              "label": "uint256"
            },
            "t_uint64": {
              "label": "uint64"
            },
            "t_bool": {
              "label": "bool"
            }
          },
          "layoutVersion": "1.2",
          "flat": false,
          "namespaces": {
            "erc7201:openzeppelin.storage.ReentrancyGuard": [
              {
                "contract": "ReentrancyGuardUpgradeable",
                "label": "_status",
                "type": "t_uint256",
                "src": "@openzeppelin/contracts-upgradeable/utils/ReentrancyGuardUpgradeable.sol:43"
              }
            ],
            "erc7201:openzeppelin.storage.Initializable": [
              {
                "contract": "Initializable",
                "label": "_initialized",
                "type": "t_uint64",
                "src": "@openzeppelin/contracts-upgradeable/proxy/utils/Initializable.sol:69"
              },
              {
                "contract": "Initializable",
                "label": "_initializing",
                "type": "t_bool",
                "src": "@openzeppelin/contracts-upgradeable/proxy/utils/Initializable.sol:73"
              }
            ]
          }
        },
        "solcVersion": "0.8.22"
      },
      "@openzeppelin/contracts-upgradeable/utils/introspection/ERC165Upgradeable.sol:ERC165Upgradeable": {
        "src": "@openzeppelin/contracts-upgradeable/utils/introspection/ERC165Upgradeable.sol:21",
        "inherit": [
          "@openzeppelin/contracts/utils/introspection/IERC165.sol:IERC165",
          "@openzeppelin/contracts-upgradeable/proxy/utils/Initializable.sol:Initializable"
        ],
        "libraries": [],
        "methods": [
          "supportsInterface(bytes4)"
        ],
        "linkReferences": [],
        "errors": [],
        "layout": {
          "storage": [],
          "types": {
            "t_uint64": {
              "label": "uint64"
            },
            "t_bool": {
              "label": "bool"
            }
          },
          "layoutVersion": "1.2",
          "flat": false,
          "namespaces": {
            "erc7201:openzeppelin.storage.Initializable": [
              {
                "contract": "Initializable",
                "label": "_initialized",
                "type": "t_uint64",
                "src": "@openzeppelin/contracts-upgradeable/proxy/utils/Initializable.sol:69"
              },
              {
                "contract": "Initializable",
                "label": "_initializing",
                "type": "t_bool",
                "src": "@openzeppelin/contracts-upgradeable/proxy/utils/Initializable.sol:73"
              }
            ]
          }
        },
        "solcVersion": "0.8.22"
      },
      "@openzeppelin/contracts/access/IAccessControl.sol:IAccessControl": {
        "src": "@openzeppelin/contracts/access/IAccessControl.sol:9",
        "inherit": [],
        "libraries": [],
        "methods": [
          "hasRole(bytes32,address)",
          "getRoleAdmin(bytes32)",
          "grantRole(bytes32,address)",
          "revokeRole(bytes32,address)",
          "renounceRole(bytes32,address)"
        ],
        "linkReferences": [],
        "errors": [],
        "layout": {
          "storage": [],
          "types": {},
          "layoutVersion": "1.2",
          "flat": false,
          "namespaces": {}
        },
        "solcVersion": "0.8.22"
      },
      "@openzeppelin/contracts/interfaces/IERC1967.sol:IERC1967": {
        "src": "@openzeppelin/contracts/interfaces/IERC1967.sol:9",
        "inherit": [],
        "libraries": [],
        "methods": [],
        "linkReferences": [],
        "errors": [],
        "layout": {
          "storage": [],
          "types": {},
          "layoutVersion": "1.2",
          "flat": false,
          "namespaces": {}
        },
        "solcVersion": "0.8.22"
      },
      "@openzeppelin/contracts/interfaces/draft-IERC1822.sol:IERC1822Proxiable": {
        "src": "@openzeppelin/contracts/interfaces/draft-IERC1822.sol:10",
        "inherit": [],
        "libraries": [],
        "methods": [
          "proxiableUUID()"
        ],
        "linkReferences": [],
        "errors": [],
        "layout": {
          "storage": [],
          "types": {},
          "layoutVersion": "1.2",
          "flat": false,
          "namespaces": {}
        },
        "solcVersion": "0.8.22"
      },
      "@openzeppelin/contracts/proxy/ERC1967/ERC1967Utils.sol:ERC1967Utils": {
        "src": "@openzeppelin/contracts/proxy/ERC1967/ERC1967Utils.sol:15",
        "version": {
          "withMetadata": "b896719c755c299135f32dbd37f0c16bb2aed3ff414a38c3d36dfac5405c55c6",
          "withoutMetadata": "e2a89a66865458f0d9fedd4bc7faf0ee62e4c341d176ab79d29bd77a1bdfc32a",
          "linkedWithoutMetadata": "e2a89a66865458f0d9fedd4bc7faf0ee62e4c341d176ab79d29bd77a1bdfc32a"
        },
        "inherit": [],
        "libraries": [
          "@openzeppelin/contracts/utils/StorageSlot.sol:StorageSlot",
          "@openzeppelin/contracts/utils/Address.sol:Address"
        ],
        "methods": [],
        "linkReferences": [],
        "errors": [
          {
            "kind": "delegatecall",
            "src": "@openzeppelin/contracts/utils/Address.sol:97"
          },
          {
            "kind": "delegatecall",
            "src": "@openzeppelin/contracts/utils/Address.sol:97"
          }
        ],
        "layout": {
          "storage": [],
          "types": {},
          "layoutVersion": "1.2",
          "flat": false,
          "namespaces": {}
        },
        "solcVersion": "0.8.22"
      },
      "@openzeppelin/contracts/proxy/beacon/IBeacon.sol:IBeacon": {
        "src": "@openzeppelin/contracts/proxy/beacon/IBeacon.sol:9",
        "inherit": [],
        "libraries": [],
        "methods": [
          "implementation()"
        ],
        "linkReferences": [],
        "errors": [],
        "layout": {
          "storage": [],
          "types": {},
          "layoutVersion": "1.2",
          "flat": false,
          "namespaces": {}
        },
        "solcVersion": "0.8.22"
      },
      "@openzeppelin/contracts/utils/Address.sol:Address": {
        "src": "@openzeppelin/contracts/utils/Address.sol:11",
        "version": {
          "withMetadata": "2de0fcb78fa368cc66b1ab0af38b4f2d75da6b8dad8886cb75a121f504829aec",
          "withoutMetadata": "e2a89a66865458f0d9fedd4bc7faf0ee62e4c341d176ab79d29bd77a1bdfc32a",
          "linkedWithoutMetadata": "e2a89a66865458f0d9fedd4bc7faf0ee62e4c341d176ab79d29bd77a1bdfc32a"
        },
        "inherit": [],
        "libraries": [
          "@openzeppelin/contracts/utils/Errors.sol:Errors"
        ],
        "methods": [],
        "linkReferences": [],
        "errors": [
          {
            "kind": "delegatecall",
            "src": "@openzeppelin/contracts/utils/Address.sol:97"
          }
        ],
        "layout": {
          "storage": [],
          "types": {},
          "layoutVersion": "1.2",
          "flat": false,
          "namespaces": {}
        },
        "solcVersion": "0.8.22"
      },
      "@openzeppelin/contracts/utils/Errors.sol:Errors": {
        "src": "@openzeppelin/contracts/utils/Errors.sol:14",
        "version": {
          "withMetadata": "473d60c0451a5db8c737caf5fa65b6c6bd0f4a946a43fd052a6204a641b40854",
          "withoutMetadata": "e2a89a66865458f0d9fedd4bc7faf0ee62e4c341d176ab79d29bd77a1bdfc32a",
          "linkedWithoutMetadata": "e2a89a66865458f0d9fedd4bc7faf0ee62e4c341d176ab79d29bd77a1bdfc32a"
        },
        "inherit": [],
        "libraries": [],
        "methods": [],
        "linkReferences": [],
        "errors": [],
        "layout": {
          "storage": [],
          "types": {},
          "layoutVersion": "1.2",
          "flat": false,
          "namespaces": {}
        },
        "solcVersion": "0.8.22"
      },
      "@openzeppelin/contracts/utils/StorageSlot.sol:StorageSlot": {
        "src": "@openzeppelin/contracts/utils/StorageSlot.sol:34",
        "version": {
          "withMetadata": "e85c0d8abaf275d0aed943cf4804f4d1746226744376f5126f3e5378de017d3a",
          "withoutMetadata": "e2a89a66865458f0d9fedd4bc7faf0ee62e4c341d176ab79d29bd77a1bdfc32a",
          "linkedWithoutMetadata": "e2a89a66865458f0d9fedd4bc7faf0ee62e4c341d176ab79d29bd77a1bdfc32a"
        },
        "inherit": [],
        "libraries": [],
        "methods": [],
        "linkReferences": [],
        "errors": [],
        "layout": {
          "storage": [],
          "types": {},
          "layoutVersion": "1.2",
          "flat": false,
          "namespaces": {}
        },
        "solcVersion": "0.8.22"
      },
      "@openzeppelin/contracts/utils/introspection/IERC165.sol:IERC165": {
        "src": "@openzeppelin/contracts/utils/introspection/IERC165.sol:15",
        "inherit": [],
        "libraries": [],
        "methods": [
          "supportsInterface(bytes4)"
        ],
        "linkReferences": [],
        "errors": [],
        "layout": {
          "storage": [],
          "types": {},
          "layoutVersion": "1.2",
          "flat": false,
          "namespaces": {}
        },
        "solcVersion": "0.8.22"
      },
      "contracts/TrafficEnforcement.sol:TrafficEnforcement": {
        "src": "contracts/TrafficEnforcement.sol:10",
        "version": {
          "withMetadata": "bd0de04ac34593130033034505d483b6a9eaa882019bfb48e6b69896921f48ef",
          "withoutMetadata": "8b67aac568cf73ac94b67ce976988c4138035677563d169678e3e9a9b65a5296",
          "linkedWithoutMetadata": "8b67aac568cf73ac94b67ce976988c4138035677563d169678e3e9a9b65a5296"
        },
        "inherit": [],
        "libraries": [],
        "methods": [
          "()",
          "registerOfficer(address,string,string)",
          "deregisterOfficer(address)",
          "isOfficerRegistered(address)",
          "logViolation(string,uint256,string,address)",
          "getViolation(bytes32)",
          "getVehicleViolations(string)",
          "getVehicleViolationCount(string)",
          "payFine(bytes32)",
          "getTotalFinesPaid()",
          "submitAppeal(bytes32,string)",
          "getAppeal(bytes32)",
          "resolveAppeal(bytes32,bool,string)",
          "getTotalViolations()",
          "getContractBalance()",
          "withdrawFunds(uint256)",
          "()",
          "()"
        ],
        "linkReferences": [],
        "errors": [
          {
            "kind": "constructor",
            "contract": "TrafficEnforcement",
            "src": "contracts/TrafficEnforcement.sol:114"
          }
        ],
        "layout": {
          "storage": [
            {
              "label": "admin",
              "offset": 0,
              "slot": "0",
              "type": "t_address",
              "contract": "TrafficEnforcement",
              "src": "contracts/TrafficEnforcement.sol:66"
            },
            {
              "label": "violations",
              "offset": 0,
              "slot": "1",
              "type": "t_mapping(t_bytes32,t_struct(Violation)2057_storage)",
              "contract": "TrafficEnforcement",
              "src": "contracts/TrafficEnforcement.sol:68"
            },
            {
              "label": "officers",
              "offset": 0,
              "slot": "2",
              "type": "t_mapping(t_address,t_struct(Officer)2069_storage)",
              "contract": "TrafficEnforcement",
              "src": "contracts/TrafficEnforcement.sol:69"
            },
            {
              "label": "vehicleViolations",
              "offset": 0,
              "slot": "3",
              "type": "t_mapping(t_string_memory_ptr,t_array(t_bytes32)dyn_storage)",
              "contract": "TrafficEnforcement",
              "src": "contracts/TrafficEnforcement.sol:70"
            },
            {
              "label": "appeals",
              "offset": 0,
              "slot": "4",
              "type": "t_mapping(t_bytes32,t_struct(Appeal)2085_storage)",
              "contract": "TrafficEnforcement",
              "src": "contracts/TrafficEnforcement.sol:71"
            },
            {
              "label": "totalViolations",
              "offset": 0,
              "slot": "5",
              "type": "t_uint256",
              "contract": "TrafficEnforcement",
              "src": "contracts/TrafficEnforcement.sol:73"
            },
            {
              "label": "totalFinesPaid",
              "offset": 0,
              "slot": "6",
              "type": "t_uint256",
              "contract": "TrafficEnforcement",
              "src": "contracts/TrafficEnforcement.sol:74"
            },
            {
              "label": "offenseFines",
              "offset": 0,
              "slot": "7",
              "type": "t_mapping(t_uint256,t_uint256)",
              "contract": "TrafficEnforcement",
              "src": "contracts/TrafficEnforcement.sol:77"
            },
            {
              "label": "offenseNames",
              "offset": 0,
              "slot": "8",
              "type": "t_mapping(t_uint256,t_string_storage)",
              "contract": "TrafficEnforcement",
              "src": "contracts/TrafficEnforcement.sol:78"
            }
          ],
          "types": {
            "t_address": {
              "label": "address",
              "numberOfBytes": "20"
            },
            "t_array(t_bytes32)dyn_storage": {
              "label": "bytes32[]",
              "numberOfBytes": "32"
            },
            "t_bool": {
              "label": "bool",
              "numberOfBytes": "1"
            },
            "t_bytes32": {
              "label": "bytes32",
              "numberOfBytes": "32"
            },
            "t_enum(ViolationStatus)2034": {
              "label": "enum TrafficEnforcement.ViolationStatus",
              "members": [
                "Unpaid",
                "Paid",
                "Appealed",
                "Waived",
                "Rejected"
              ],
              "numberOfBytes": "1"
            },
            "t_mapping(t_address,t_struct(Officer)2069_storage)": {
              "label": "mapping(address => struct TrafficEnforcement.Officer)",
              "numberOfBytes": "32"
            },
            "t_mapping(t_bytes32,t_struct(Appeal)2085_storage)": {
              "label": "mapping(bytes32 => struct TrafficEnforcement.Appeal)",
              "numberOfBytes": "32"
            },
            "t_mapping(t_bytes32,t_struct(Violation)2057_storage)": {
              "label": "mapping(bytes32 => struct TrafficEnforcement.Violation)",
              "numberOfBytes": "32"
            },
            "t_mapping(t_string_memory_ptr,t_array(t_bytes32)dyn_storage)": {
              "label": "mapping(string => bytes32[])",
              "numberOfBytes": "32"
            },
            "t_mapping(t_uint256,t_string_storage)": {
              "label": "mapping(uint256 => string)",
              "numberOfBytes": "32"
            },
            "t_mapping(t_uint256,t_uint256)": {
              "label": "mapping(uint256 => uint256)",
              "numberOfBytes": "32"
            },
            "t_string_memory_ptr": {
              "label": "string",
              "numberOfBytes": "32"
            },
            "t_string_storage": {
              "label": "string",
              "numberOfBytes": "32"
            },
            "t_struct(Appeal)2085_storage": {
              "label": "struct TrafficEnforcement.Appeal",
              "members": [
                {
                  "label": "violationId",
                  "type": "t_bytes32",
                  "offset": 0,
                  "slot": "0"
                },
                {
                  "label": "driverId",
                  "type": "t_address",
                  "offset": 0,
                  "slot": "1"
                },
                {
                  "label": "appealReason",
                  "type": "t_string_storage",
                  "offset": 0,
                  "slot": "2"
                },
                {
                  "label": "appealTime",
                  "type": "t_uint256",
                  "offset": 0,
                  "slot": "3"
                },
                {
                  "label": "resolved",
                  "type": "t_bool",
                  "offset": 0,
                  "slot": "4"
                },
                {
                  "label": "waived",
                  "type": "t_bool",
                  "offset": 1,
                  "slot": "4"
                },
                {
                  "label": "judgeNotes",
                  "type": "t_string_storage",
                  "offset": 0,
                  "slot": "5"
                }
              ],
              "numberOfBytes": "192"
            },
            "t_struct(Officer)2069_storage": {
              "label": "struct TrafficEnforcement.Officer",
              "members": [
                {
                  "label": "officerId",
                  "type": "t_address",
                  "offset": 0,
                  "slot": "0"
                },
                {
                  "label": "name",
                  "type": "t_string_storage",
                  "offset": 0,
                  "slot": "1"
                },
                {
                  "label": "badgeNumber",
                  "type": "t_string_storage",
                  "offset": 0,
                  "slot": "2"
                },
                {
                  "label": "isRegistered",
                  "type": "t_bool",
                  "offset": 0,
                  "slot": "3"
                },
                {
                  "label": "registrationTime",
                  "type": "t_uint256",
                  "offset": 0,
                  "slot": "4"
                }
              ],
              "numberOfBytes": "160"
            },
            "t_struct(Violation)2057_storage": {
              "label": "struct TrafficEnforcement.Violation",
              "members": [
                {
                  "label": "violationId",
                  "type": "t_bytes32",
                  "offset": 0,
                  "slot": "0"
                },
                {
                  "label": "vehicleId",
                  "type": "t_string_storage",
                  "offset": 0,
                  "slot": "1"
                },
                {
                  "label": "officerId",
                  "type": "t_address",
                  "offset": 0,
                  "slot": "2"
                },
                {
                  "label": "offenseCode",
                  "type": "t_uint256",
                  "offset": 0,
                  "slot": "3"
                },
                {
                  "label": "evidenceHash",
                  "type": "t_string_storage",
                  "offset": 0,
                  "slot": "4"
                },
                {
                  "label": "timestamp",
                  "type": "t_uint256",
                  "offset": 0,
                  "slot": "5"
                },
                {
                  "label": "fineAmount",
                  "type": "t_uint256",
                  "offset": 0,
                  "slot": "6"
                },
                {
                  "label": "status",
                  "type": "t_enum(ViolationStatus)2034",
                  "offset": 0,
                  "slot": "7"
                },
                {
                  "label": "driverId",
                  "type": "t_address",
                  "offset": 1,
                  "slot": "7"
                },
                {
                  "label": "offenseName",
                  "type": "t_string_storage",
                  "offset": 0,
                  "slot": "8"
                }
              ],
              "numberOfBytes": "288"
            },
            "t_uint256": {
              "label": "uint256",
              "numberOfBytes": "32"
            }
          },
          "layoutVersion": "1.2",
          "flat": true,
          "namespaces": {}
        },
        "solcVersion": "0.8.22"
      },
      "contracts/TrafficEnforcementV2.sol:TrafficEnforcementV2": {
        "src": "contracts/TrafficEnforcementV2.sol:26",
        "version": {
          "withMetadata": "a624cb4579873bae8ab9ac5b4b8919195a528f4fdf1785069d9d93e7a790b0f3",
          "withoutMetadata": "2a2beadb7e0788e53143049f7e8cb15642cde103afbf56a2c42c41859cffd10d",
          "linkedWithoutMetadata": "2a2beadb7e0788e53143049f7e8cb15642cde103afbf56a2c42c41859cffd10d"
        },
        "inherit": [
          "@openzeppelin/contracts-upgradeable/proxy/utils/UUPSUpgradeable.sol:UUPSUpgradeable",
          "@openzeppelin/contracts/interfaces/draft-IERC1822.sol:IERC1822Proxiable",
          "@openzeppelin/contracts-upgradeable/utils/ReentrancyGuardUpgradeable.sol:ReentrancyGuardUpgradeable",
          "@openzeppelin/contracts-upgradeable/utils/PausableUpgradeable.sol:PausableUpgradeable",
          "@openzeppelin/contracts-upgradeable/access/AccessControlUpgradeable.sol:AccessControlUpgradeable",
          "@openzeppelin/contracts-upgradeable/utils/introspection/ERC165Upgradeable.sol:ERC165Upgradeable",
          "@openzeppelin/contracts/utils/introspection/IERC165.sol:IERC165",
          "@openzeppelin/contracts/access/IAccessControl.sol:IAccessControl",
          "@openzeppelin/contracts-upgradeable/utils/ContextUpgradeable.sol:ContextUpgradeable",
          "@openzeppelin/contracts-upgradeable/proxy/utils/Initializable.sol:Initializable"
        ],
        "libraries": [],
        "methods": [
          "initialize(address)",
          "registerOfficer(address,string,string)",
          "deactivateOfficer(address)",
          "isOfficerActive(address)",
          "logViolation(string,uint32,string,address)",
          "getViolation(bytes32)",
          "getVehicleViolations(string,uint256,uint256)",
          "payFine(bytes32)",
          "submitAppeal(bytes32,string)",
          "resolveAppeal(bytes32,bool,string)",
          "claimRefund()",
          "updateOffense(uint32,uint256,string,bool)",
          "withdrawFunds(address,uint256)",
          "pause()",
          "unpause()",
          "()",
          "()"
        ],
        "linkReferences": [],
        "errors": [],
        "layout": {
          "storage": [
            {
              "label": "violations",
              "offset": 0,
              "slot": "0",
              "type": "t_mapping(t_bytes32,t_struct(Violation)3137_storage)",
              "contract": "TrafficEnforcementV2",
              "src": "contracts/TrafficEnforcementV2.sol:149"
            },
            {
              "label": "officers",
              "offset": 0,
              "slot": "1",
              "type": "t_mapping(t_address,t_struct(Officer)3153_storage)",
              "contract": "TrafficEnforcementV2",
              "src": "contracts/TrafficEnforcementV2.sol:150"
            },
            {
              "label": "vehicleViolations",
              "offset": 0,
              "slot": "2",
              "type": "t_mapping(t_string_memory_ptr,t_array(t_bytes32)dyn_storage)",
              "contract": "TrafficEnforcementV2",
              "src": "contracts/TrafficEnforcementV2.sol:151"
            },
            {
              "label": "appeals",
              "offset": 0,
              "slot": "3",
              "type": "t_mapping(t_bytes32,t_struct(Appeal)3175_storage)",
              "contract": "TrafficEnforcementV2",
              "src": "contracts/TrafficEnforcementV2.sol:152"
            },
            {
              "label": "offenses",
              "offset": 0,
              "slot": "4",
              "type": "t_mapping(t_uint32,t_struct(Offense)3183_storage)",
              "contract": "TrafficEnforcementV2",
              "src": "contracts/TrafficEnforcementV2.sol:153"
            },
            {
              "label": "totalViolations",
              "offset": 0,
              "slot": "5",
              "type": "t_uint256",
              "contract": "TrafficEnforcementV2",
              "src": "contracts/TrafficEnforcementV2.sol:158"
            },
            {
              "label": "totalFinesPaid",
              "offset": 0,
              "slot": "6",
              "type": "t_uint256",
              "contract": "TrafficEnforcementV2",
              "src": "contracts/TrafficEnforcementV2.sol:159"
            },
            {
              "label": "totalFinesRefunded",
              "offset": 0,
              "slot": "7",
              "type": "t_uint256",
              "contract": "TrafficEnforcementV2",
              "src": "contracts/TrafficEnforcementV2.sol:160"
            },
            {
              "label": "officerDailyViolations",
              "offset": 0,
              "slot": "8",
              "type": "t_mapping(t_address,t_mapping(t_uint256,t_uint256))",
              "contract": "TrafficEnforcementV2",
              "src": "contracts/TrafficEnforcementV2.sol:165"
            },
            {
              "label": "pendingRefunds",
              "offset": 0,
              "slot": "9",
              "type": "t_mapping(t_address,t_uint256)",
              "contract": "TrafficEnforcementV2",
              "src": "contracts/TrafficEnforcementV2.sol:170"
            },
            {
              "label": "version",
              "offset": 0,
              "slot": "10",
              "type": "t_uint256",
              "contract": "TrafficEnforcementV2",
              "src": "contracts/TrafficEnforcementV2.sol:175"
            }
          ],
          "types": {
            "t_address": {
              "label": "address",
              "numberOfBytes": "20"
            },
            "t_array(t_bytes32)dyn_storage": {
              "label": "bytes32[]",
              "numberOfBytes": "32"
            },
            "t_bool": {
              "label": "bool",
              "numberOfBytes": "1"
            },
            "t_bytes32": {
              "label": "bytes32",
              "numberOfBytes": "32"
            },
            "t_enum(ViolationStatus)3112": {
              "label": "enum TrafficEnforcementV2.ViolationStatus",
              "members": [
                "Unpaid",
                "Paid",
                "Appealed",
                "Waived",
                "Rejected",
                "Refunded"
              ],
              "numberOfBytes": "1"
            },
            "t_mapping(t_address,t_mapping(t_uint256,t_uint256))": {
              "label": "mapping(address => mapping(uint256 => uint256))",
              "numberOfBytes": "32"
            },
            "t_mapping(t_address,t_struct(Officer)3153_storage)": {
              "label": "mapping(address => struct TrafficEnforcementV2.Officer)",
              "numberOfBytes": "32"
            },
            "t_mapping(t_address,t_uint256)": {
              "label": "mapping(address => uint256)",
              "numberOfBytes": "32"
            },
            "t_mapping(t_bytes32,t_struct(Appeal)3175_storage)": {
              "label": "mapping(bytes32 => struct TrafficEnforcementV2.Appeal)",
              "numberOfBytes": "32"
            },
            "t_mapping(t_bytes32,t_struct(Violation)3137_storage)": {
              "label": "mapping(bytes32 => struct TrafficEnforcementV2.Violation)",
              "numberOfBytes": "32"
            },
            "t_mapping(t_string_memory_ptr,t_array(t_bytes32)dyn_storage)": {
              "label": "mapping(string => bytes32[])",
              "numberOfBytes": "32"
            },
            "t_mapping(t_uint256,t_uint256)": {
              "label": "mapping(uint256 => uint256)",
              "numberOfBytes": "32"
            },
            "t_mapping(t_uint32,t_struct(Offense)3183_storage)": {
              "label": "mapping(uint32 => struct TrafficEnforcementV2.Offense)",
              "numberOfBytes": "32"
            },
            "t_string_memory_ptr": {
              "label": "string",
              "numberOfBytes": "32"
            },
            "t_string_storage": {
              "label": "string",
              "numberOfBytes": "32"
            },
            "t_struct(Appeal)3175_storage": {
              "label": "struct TrafficEnforcementV2.Appeal",
              "members": [
                {
                  "label": "violationId",
                  "type": "t_bytes32",
                  "offset": 0,
                  "slot": "0"
                },
                {
                  "label": "appellant",
                  "type": "t_address",
                  "offset": 0,
                  "slot": "1"
                },
                {
                  "label": "appealReason",
                  "type": "t_string_storage",
                  "offset": 0,
                  "slot": "2"
                },
                {
                  "label": "appealTime",
                  "type": "t_uint256",
                  "offset": 0,
                  "slot": "3"
                },
                {
                  "label": "resolved",
                  "type": "t_bool",
                  "offset": 0,
                  "slot": "4"
                },
                {
                  "label": "approved",
                  "type": "t_bool",
                  "offset": 1,
                  "slot": "4"
                },
                {
                  "label": "resolution",
                  "type": "t_string_storage",
                  "offset": 0,
                  "slot": "5"
                },
                {
                  "label": "resolvedBy",
                  "type": "t_address",
                  "offset": 0,
                  "slot": "6"
                },
                {
                  "label": "appealCount",
                  "type": "t_uint256",
                  "offset": 0,
                  "slot": "7"
                },
                {
                  "label": "lastAppealTime",
                  "type": "t_uint256",
                  "offset": 0,
                  "slot": "8"
                }
              ],
              "numberOfBytes": "288"
            },
            "t_struct(Offense)3183_storage": {
              "label": "struct TrafficEnforcementV2.Offense",
              "members": [
                {
                  "label": "fineAmountKES",
                  "type": "t_uint256",
                  "offset": 0,
                  "slot": "0"
                },
                {
                  "label": "name",
                  "type": "t_string_storage",
                  "offset": 0,
                  "slot": "1"
                },
                {
                  "label": "isActive",
                  "type": "t_bool",
                  "offset": 0,
                  "slot": "2"
                }
              ],
              "numberOfBytes": "96"
            },
            "t_struct(Officer)3153_storage": {
              "label": "struct TrafficEnforcementV2.Officer",
              "members": [
                {
                  "label": "officerId",
                  "type": "t_address",
                  "offset": 0,
                  "slot": "0"
                },
                {
                  "label": "name",
                  "type": "t_string_storage",
                  "offset": 0,
                  "slot": "1"
                },
                {
                  "label": "badgeNumber",
                  "type": "t_string_storage",
                  "offset": 0,
                  "slot": "2"
                },
                {
                  "label": "isActive",
                  "type": "t_bool",
                  "offset": 0,
                  "slot": "3"
                },
                {
                  "label": "registrationTime",
                  "type": "t_uint256",
                  "offset": 0,
                  "slot": "4"
                },
                {
                  "label": "dailyViolationCount",
                  "type": "t_uint256",
                  "offset": 0,
                  "slot": "5"
                },
                {
                  "label": "lastViolationDate",
                  "type": "t_uint256",
                  "offset": 0,
                  "slot": "6"
                }
              ],
              "numberOfBytes": "224"
            },
            "t_struct(Violation)3137_storage": {
              "label": "struct TrafficEnforcementV2.Violation",
              "members": [
                {
                  "label": "violationId",
                  "type": "t_bytes32",
                  "offset": 0,
                  "slot": "0"
                },
                {
                  "label": "vehicleId",
                  "type": "t_string_storage",
                  "offset": 0,
                  "slot": "1"
                },
                {
                  "label": "officerId",
                  "type": "t_address",
                  "offset": 0,
                  "slot": "2"
                },
                {
                  "label": "offenseCode",
                  "type": "t_uint32",
                  "offset": 20,
                  "slot": "2"
                },
                {
                  "label": "evidenceHash",
                  "type": "t_string_storage",
                  "offset": 0,
                  "slot": "3"
                },
                {
                  "label": "timestamp",
                  "type": "t_uint256",
                  "offset": 0,
                  "slot": "4"
                },
                {
                  "label": "fineAmount",
                  "type": "t_uint256",
                  "offset": 0,
                  "slot": "5"
                },
                {
                  "label": "status",
                  "type": "t_enum(ViolationStatus)3112",
                  "offset": 0,
                  "slot": "6"
                },
                {
                  "label": "driverId",
                  "type": "t_address",
                  "offset": 1,
                  "slot": "6"
                },
                {
                  "label": "paidAmount",
                  "type": "t_uint256",
                  "offset": 0,
                  "slot": "7"
                },
                {
                  "label": "paidBy",
                  "type": "t_address",
                  "offset": 0,
                  "slot": "8"
                }
              ],
              "numberOfBytes": "288"
            },
            "t_uint256": {
              "label": "uint256",
              "numberOfBytes": "32"
            },
            "t_uint32": {
              "label": "uint32",
              "numberOfBytes": "4"
            },
            "t_mapping(t_bytes32,t_struct(RoleData)27_storage)": {
              "label": "mapping(bytes32 => struct AccessControlUpgradeable.RoleData)"
            },
            "t_struct(RoleData)27_storage": {
              "label": "struct AccessControlUpgradeable.RoleData",
              "members": [
                {
                  "label": "hasRole",
                  "type": "t_mapping(t_address,t_bool)"
                },
                {
                  "label": "adminRole",
                  "type": "t_bytes32"
                }
              ]
            },
            "t_mapping(t_address,t_bool)": {
              "label": "mapping(address => bool)"
            },
            "t_uint64": {
              "label": "uint64"
            }
          },
          "layoutVersion": "1.2",
          "flat": true,
          "namespaces": {
            "erc7201:openzeppelin.storage.ReentrancyGuard": [
              {
                "contract": "ReentrancyGuardUpgradeable",
                "label": "_status",
                "type": "t_uint256",
                "src": "@openzeppelin/contracts-upgradeable/utils/ReentrancyGuardUpgradeable.sol:43"
              }
            ],
            "erc7201:openzeppelin.storage.Pausable": [
              {
                "contract": "PausableUpgradeable",
                "label": "_paused",
                "type": "t_bool",
                "src": "@openzeppelin/contracts-upgradeable/utils/PausableUpgradeable.sol:21"
              }
            ],
            "erc7201:openzeppelin.storage.AccessControl": [
              {
                "contract": "AccessControlUpgradeable",
                "label": "_roles",
                "type": "t_mapping(t_bytes32,t_struct(RoleData)27_storage)",
                "src": "@openzeppelin/contracts-upgradeable/access/AccessControlUpgradeable.sol:62"
              }
            ],
            "erc7201:openzeppelin.storage.Initializable": [
              {
                "contract": "Initializable",
                "label": "_initialized",
                "type": "t_uint64",
                "src": "@openzeppelin/contracts-upgradeable/proxy/utils/Initializable.sol:69"
              },
              {
                "contract": "Initializable",
                "label": "_initializing",
                "type": "t_bool",
                "src": "@openzeppelin/contracts-upgradeable/proxy/utils/Initializable.sol:73"
              }
            ]
          }
        },
        "solcVersion": "0.8.22"
      }
    },
    {
      "@openzeppelin/contracts-upgradeable/access/AccessControlUpgradeable.sol:AccessControlUpgradeable": {
        "src": "@openzeppelin/contracts-upgradeable/access/AccessControlUpgradeable.sol:51",
        "inherit": [
          "@openzeppelin/contracts-upgradeable/utils/introspection/ERC165Upgradeable.sol:ERC165Upgradeable",
          "@openzeppelin/contracts/utils/introspection/IERC165.sol:IERC165",
          "@openzeppelin/contracts/access/IAccessControl.sol:IAccessControl",
          "@openzeppelin/contracts-upgradeable/utils/ContextUpgradeable.sol:ContextUpgradeable",
          "@openzeppelin/contracts-upgradeable/proxy/utils/Initializable.sol:Initializable"
        ],
        "libraries": [],
        "methods": [
          "supportsInterface(bytes4)",
          "hasRole(bytes32,address)",
          "getRoleAdmin(bytes32)",
          "grantRole(bytes32,address)",
          "revokeRole(bytes32,address)",
          "renounceRole(bytes32,address)"
        ],
        "linkReferences": [],
        "errors": [],
        "layout": {
          "storage": [],
          "types": {
            "t_mapping(t_bytes32,t_struct(RoleData)27_storage)": {
              "label": "mapping(bytes32 => struct AccessControlUpgradeable.RoleData)"
            },
            "t_bytes32": {
              "label": "bytes32"
            },
            "t_struct(RoleData)27_storage": {
              "label": "struct AccessControlUpgradeable.RoleData",
              "members": [
                {
                  "label": "hasRole",
                  "type": "t_mapping(t_address,t_bool)"
                },
                {
                  "label": "adminRole",
                  "type": "t_bytes32"
                }
              ]
            },
            "t_mapping(t_address,t_bool)": {
              "label": "mapping(address => bool)"
            },
            "t_address": {
              "label": "address"
            },
            "t_bool": {
              "label": "bool"
            },
            "t_uint64": {
              "label": "uint64"
            }
          },
          "layoutVersion": "1.2",
          "flat": false,
          "namespaces": {
            "erc7201:openzeppelin.storage.AccessControl": [
              {
                "contract": "AccessControlUpgradeable",
                "label": "_roles",
                "type": "t_mapping(t_bytes32,t_struct(RoleData)27_storage)",
                "src": "@openzeppelin/contracts-upgradeable/access/AccessControlUpgradeable.sol:62"
              }
            ],
            "erc7201:openzeppelin.storage.Initializable": [
              {
                "contract": "Initializable",
                "label": "_initialized",
                "type": "t_uint64",
                "src": "@openzeppelin/contracts-upgradeable/proxy/utils/Initializable.sol:69"
              },
              {
                "contract": "Initializable",
                "label": "_initializing",
                "type": "t_bool",
                "src": "@openzeppelin/contracts-upgradeable/proxy/utils/Initializable.sol:73"
              }
            ]
          }
        },
        "solcVersion": "0.8.22"
      },
      "@openzeppelin/contracts-upgradeable/proxy/utils/Initializable.sol:Initializable": {
        "src": "@openzeppelin/contracts-upgradeable/proxy/utils/Initializable.sol:56",
        "inherit": [],
        "libraries": [],
        "methods": [],
        "linkReferences": [],
        "errors": [],
        "layout": {
          "storage": [],
          "types": {
            "t_uint64": {
              "label": "uint64"
            },
            "t_bool": {
              "label": "bool"
            }
          },
          "layoutVersion": "1.2",
          "flat": false,
          "namespaces": {
            "erc7201:openzeppelin.storage.Initializable": [
              {
                "contract": "Initializable",
                "label": "_initialized",
                "type": "t_uint64",
                "src": "@openzeppelin/contracts-upgradeable/proxy/utils/Initializable.sol:69"
              },
              {
                "contract": "Initializable",
                "label": "_initializing",
                "type": "t_bool",
                "src": "@openzeppelin/contracts-upgradeable/proxy/utils/Initializable.sol:73"
              }
            ]
          }
        },
        "solcVersion": "0.8.22"
      },
      "@openzeppelin/contracts-upgradeable/proxy/utils/UUPSUpgradeable.sol:UUPSUpgradeable": {
        "src": "@openzeppelin/contracts-upgradeable/proxy/utils/UUPSUpgradeable.sol:20",
        "inherit": [
          "@openzeppelin/contracts/interfaces/draft-IERC1822.sol:IERC1822Proxiable",
          "@openzeppelin/contracts-upgradeable/proxy/utils/Initializable.sol:Initializable"
        ],
        "libraries": [
          "@openzeppelin/contracts/proxy/ERC1967/ERC1967Utils.sol:ERC1967Utils"
        ],
        "methods": [
          "proxiableUUID()",
          "upgradeToAndCall(address,bytes)"
        ],
        "linkReferences": [],
        "errors": [
          {
            "kind": "delegatecall",
            "src": "@openzeppelin/contracts/utils/Address.sol:97"
          }
        ],
        "layout": {
          "storage": [],
          "types": {
            "t_uint64": {
              "label": "uint64"
            },
            "t_bool": {
              "label": "bool"
            }
          },
          "layoutVersion": "1.2",
          "flat": false,
          "namespaces": {
            "erc7201:openzeppelin.storage.Initializable": [
              {
                "contract": "Initializable",
                "label": "_initialized",
                "type": "t_uint64",
                "src": "@openzeppelin/contracts-upgradeable/proxy/utils/Initializable.sol:69"
              },
              {
                "contract": "Initializable",
                "label": "_initializing",
                "type": "t_bool",
                "src": "@openzeppelin/contracts-upgradeable/proxy/utils/Initializable.sol:73"
              }
            ]
          }
        },
        "solcVersion": "0.8.22"
      },
      "@openzeppelin/contracts-upgradeable/utils/ContextUpgradeable.sol:ContextUpgradeable": {
        "src": "@openzeppelin/contracts-upgradeable/utils/ContextUpgradeable.sol:17",
        "inherit": [
          "@openzeppelin/contracts-upgradeable/proxy/utils/Initializable.sol:Initializable"
        ],
        "libraries": [],
        "methods": [],
        "linkReferences": [],
        "errors": [],
        "layout": {
          "storage": [],
          "types": {
            "t_uint64": {
              "label": "uint64"
            },
            "t_bool": {
              "label": "bool"
            }
          },
          "layoutVersion": "1.2",
          "flat": false,
          "namespaces": {
            "erc7201:openzeppelin.storage.Initializable": [
              {
                "contract": "Initializable",
                "label": "_initialized",
                "type": "t_uint64",
                "src": "@openzeppelin/contracts-upgradeable/proxy/utils/Initializable.sol:69"
              },
              {
                "contract": "Initializable",
                "label": "_initializing",
                "type": "t_bool",
                "src": "@openzeppelin/contracts-upgradeable/proxy/utils/Initializable.sol:73"
              }
            ]
          }
        },
        "solcVersion": "0.8.22"
      },
      "@openzeppelin/contracts-upgradeable/utils/PausableUpgradeable.sol:PausableUpgradeable": {
        "src": "@openzeppelin/contracts-upgradeable/utils/PausableUpgradeable.sol:18",
        "inherit": [
          "@openzeppelin/contracts-upgradeable/utils/ContextUpgradeable.sol:ContextUpgradeable",
          "@openzeppelin/contracts-upgradeable/proxy/utils/Initializable.sol:Initializable"
        ],
        "libraries": [],
        "methods": [
          "paused()"
        ],
        "linkReferences": [],
        "errors": [],
        "layout": {
          "storage": [],
          "types": {
            "t_bool": {
              "label": "bool"
            },
            "t_uint64": {
              "label": "uint64"
            }
          },
          "layoutVersion": "1.2",
          "flat": false,
          "namespaces": {
            "erc7201:openzeppelin.storage.Pausable": [
              {
                "contract": "PausableUpgradeable",
                "label": "_paused",
                "type": "t_bool",
                "src": "@openzeppelin/contracts-upgradeable/utils/PausableUpgradeable.sol:21"
              }
            ],
            "erc7201:openzeppelin.storage.Initializable": [
              {
                "contract": "Initializable",
                "label": "_initialized",
                "type": "t_uint64",
                "src": "@openzeppelin/contracts-upgradeable/proxy/utils/Initializable.sol:69"
              },
              {
                "contract": "Initializable",
                "label": "_initializing",
                "type": "t_bool",
                "src": "@openzeppelin/contracts-upgradeable/proxy/utils/Initializable.sol:73"
              }
            ]
          }
        },
        "solcVersion": "0.8.22"
      },
      "@openzeppelin/contracts-upgradeable/utils/ReentrancyGuardUpgradeable.sol:ReentrancyGuardUpgradeable": {
        "src": "@openzeppelin/contracts-upgradeable/utils/ReentrancyGuardUpgradeable.sol:26",
        "inherit": [
          "@openzeppelin/contracts-upgradeable/proxy/utils/Initializable.sol:Initializable"
        ],
        "libraries": [],
        "methods": [],
        "linkReferences": [],
        "errors": [],
        "layout": {
          "storage": [],
          "types": {
            "t_uint256": {
              "label": "uint256"
            },
            "t_uint64": {
              "label": "uint64"
            },
            "t_bool": {
              "label": "bool"
            }
          },
          "layoutVersion": "1.2",
          "flat": false,
          "namespaces": {
            "erc7201:openzeppelin.storage.ReentrancyGuard": [
              {
                "contract": "ReentrancyGuardUpgradeable",
                "label": "_status",
                "type": "t_uint256",
                "src": "@openzeppelin/contracts-upgradeable/utils/ReentrancyGuardUpgradeable.sol:43"
              }
            ],
            "erc7201:openzeppelin.storage.Initializable": [
              {
                "contract": "Initializable",
                "label": "_initialized",
                "type": "t_uint64",
                "src": "@openzeppelin/contracts-upgradeable/proxy/utils/Initializable.sol:69"
              },
              {
                "contract": "Initializable",
                "label": "_initializing",
                "type": "t_bool",
                "src": "@openzeppelin/contracts-upgradeable/proxy/utils/Initializable.sol:73"
              }
            ]
          }
        },
        "solcVersion": "0.8.22"
      },
      "@openzeppelin/contracts-upgradeable/utils/introspection/ERC165Upgradeable.sol:ERC165Upgradeable": {
        "src": "@openzeppelin/contracts-upgradeable/utils/introspection/ERC165Upgradeable.sol:21",
        "inherit": [
          "@openzeppelin/contracts/utils/introspection/IERC165.sol:IERC165",
          "@openzeppelin/contracts-upgradeable/proxy/utils/Initializable.sol:Initializable"
        ],
        "libraries": [],
        "methods": [
          "supportsInterface(bytes4)"
        ],
        "linkReferences": [],
        "errors": [],
        "layout": {
          "storage": [],
          "types": {
            "t_uint64": {
              "label": "uint64"
            },
            "t_bool": {
              "label": "bool"
            }
          },
          "layoutVersion": "1.2",
          "flat": false,
          "namespaces": {
            "erc7201:openzeppelin.storage.Initializable": [
              {
                "contract": "Initializable",
                "label": "_initialized",
                "type": "t_uint64",
                "src": "@openzeppelin/contracts-upgradeable/proxy/utils/Initializable.sol:69"
              },
              {
                "contract": "Initializable",
                "label": "_initializing",
                "type": "t_bool",
                "src": "@openzeppelin/contracts-upgradeable/proxy/utils/Initializable.sol:73"
              }
            ]
          }
        },
        "solcVersion": "0.8.22"
      },
      "@openzeppelin/contracts/access/IAccessControl.sol:IAccessControl": {
        "src": "@openzeppelin/contracts/access/IAccessControl.sol:9",
        "inherit": [],
        "libraries": [],
        "methods": [
          "hasRole(bytes32,address)",
          "getRoleAdmin(bytes32)",
          "grantRole(bytes32,address)",
          "revokeRole(bytes32,address)",
          "renounceRole(bytes32,address)"
        ],
        "linkReferences": [],
        "errors": [],
        "layout": {
          "storage": [],
          "types": {},
          "layoutVersion": "1.2",
          "flat": false,
          "namespaces": {}
        },
        "solcVersion": "0.8.22"
      },
      "@openzeppelin/contracts/interfaces/IERC1967.sol:IERC1967": {
        "src": "@openzeppelin/contracts/interfaces/IERC1967.sol:9",
        "inherit": [],
        "libraries": [],
        "methods": [],
        "linkReferences": [],
        "errors": [],
        "layout": {
          "storage": [],
          "types": {},
          "layoutVersion": "1.2",
          "flat": false,
          "namespaces": {}
        },
        "solcVersion": "0.8.22"
      },
      "@openzeppelin/contracts/interfaces/draft-IERC1822.sol:IERC1822Proxiable": {
        "src": "@openzeppelin/contracts/interfaces/draft-IERC1822.sol:10",
        "inherit": [],
        "libraries": [],
        "methods": [
          "proxiableUUID()"
        ],
        "linkReferences": [],
        "errors": [],
        "layout": {
          "storage": [],
          "types": {},
          "layoutVersion": "1.2",
          "flat": false,
          "namespaces": {}
        },
        "solcVersion": "0.8.22"
      },
      "@openzeppelin/contracts/proxy/ERC1967/ERC1967Utils.sol:ERC1967Utils": {
        "src": "@openzeppelin/contracts/proxy/ERC1967/ERC1967Utils.sol:15",
        "version": {
          "withMetadata": "b896719c755c299135f32dbd37f0c16bb2aed3ff414a38c3d36dfac5405c55c6",
          "withoutMetadata": "e2a89a66865458f0d9fedd4bc7faf0ee62e4c341d176ab79d29bd77a1bdfc32a",
          "linkedWithoutMetadata": "e2a89a66865458f0d9fedd4bc7faf0ee62e4c341d176ab79d29bd77a1bdfc32a"
        },
        "inherit": [],
        "libraries": [
          "@openzeppelin/contracts/utils/StorageSlot.sol:StorageSlot",
          "@openzeppelin/contracts/utils/Address.sol:Address"
        ],
        "methods": [],
        "linkReferences": [],
        "errors": [
          {
            "kind": "delegatecall",
            "src": "@openzeppelin/contracts/utils/Address.sol:97"
          },
          {
            "kind": "delegatecall",
            "src": "@openzeppelin/contracts/utils/Address.sol:97"
          }
        ],
        "layout": {
          "storage": [],
          "types": {},
          "layoutVersion": "1.2",
          "flat": false,
          "namespaces": {}
        },
        "solcVersion": "0.8.22"
      },
      "@openzeppelin/contracts/proxy/beacon/IBeacon.sol:IBeacon": {
        "src": "@openzeppelin/contracts/proxy/beacon/IBeacon.sol:9",
        "inherit": [],
        "libraries": [],
        "methods": [
          "implementation()"
        ],
        "linkReferences": [],
        "errors": [],
        "layout": {
          "storage": [],
          "types": {},
          "layoutVersion": "1.2",
          "flat": false,
          "namespaces": {}
        },
        "solcVersion": "0.8.22"
      },
      "@openzeppelin/contracts/utils/Address.sol:Address": {
        "src": "@openzeppelin/contracts/utils/Address.sol:11",
        "version": {
          "withMetadata": "2de0fcb78fa368cc66b1ab0af38b4f2d75da6b8dad8886cb75a121f504829aec",
          "withoutMetadata": "e2a89a66865458f0d9fedd4bc7faf0ee62e4c341d176ab79d29bd77a1bdfc32a",
          "linkedWithoutMetadata": "e2a89a66865458f0d9fedd4bc7faf0ee62e4c341d176ab79d29bd77a1bdfc32a"
        },
        "inherit": [],
        "libraries": [
          "@openzeppelin/contracts/utils/Errors.sol:Errors"
        ],
        "methods": [],
        "linkReferences": [],
        "errors": [
          {
            "kind": "delegatecall",
            "src": "@openzeppelin/contracts/utils/Address.sol:97"
          }
        ],
        "layout": {
          "storage": [],
          "types": {},
          "layoutVersion": "1.2",
          "flat": false,
          "namespaces": {}
        },
        "solcVersion": "0.8.22"
      },
      "@openzeppelin/contracts/utils/Errors.sol:Errors": {
        "src": "@openzeppelin/contracts/utils/Errors.sol:14",
        "version": {
          "withMetadata": "473d60c0451a5db8c737caf5fa65b6c6bd0f4a946a43fd052a6204a641b40854",
          "withoutMetadata": "e2a89a66865458f0d9fedd4bc7faf0ee62e4c341d176ab79d29bd77a1bdfc32a",
          "linkedWithoutMetadata": "e2a89a66865458f0d9fedd4bc7faf0ee62e4c341d176ab79d29bd77a1bdfc32a"
        },
        "inherit": [],
        "libraries": [],
        "methods": [],
        "linkReferences": [],
        "errors": [],
        "layout": {
          "storage": [],
          "types": {},
          "layoutVersion": "1.2",
          "flat": false,
          "namespaces": {}
        },
        "solcVersion": "0.8.22"
      },
      "@openzeppelin/contracts/utils/StorageSlot.sol:StorageSlot": {
        "src": "@openzeppelin/contracts/utils/StorageSlot.sol:34",
        "version": {
          "withMetadata": "e85c0d8abaf275d0aed943cf4804f4d1746226744376f5126f3e5378de017d3a",
          "withoutMetadata": "e2a89a66865458f0d9fedd4bc7faf0ee62e4c341d176ab79d29bd77a1bdfc32a",
          "linkedWithoutMetadata": "e2a89a66865458f0d9fedd4bc7faf0ee62e4c341d176ab79d29bd77a1bdfc32a"
        },
        "inherit": [],
        "libraries": [],
        "methods": [],
        "linkReferences": [],
        "errors": [],
        "layout": {
          "storage": [],
          "types": {},
          "layoutVersion": "1.2",
          "flat": false,
          "namespaces": {}
        },
        "solcVersion": "0.8.22"
      },
      "@openzeppelin/contracts/utils/introspection/IERC165.sol:IERC165": {
        "src": "@openzeppelin/contracts/utils/introspection/IERC165.sol:15",
        "inherit": [],
        "libraries": [],
        "methods": [
          "supportsInterface(bytes4)"
        ],
        "linkReferences": [],
        "errors": [],
        "layout": {
          "storage": [],
          "types": {},
          "layoutVersion": "1.2",
          "flat": false,
          "namespaces": {}
        },
        "solcVersion": "0.8.22"
      },
      "contracts/TrafficEnforcement.sol:TrafficEnforcement": {
        "src": "contracts/TrafficEnforcement.sol:10",
        "version": {
          "withMetadata": "bd0de04ac34593130033034505d483b6a9eaa882019bfb48e6b69896921f48ef",
          "withoutMetadata": "8b67aac568cf73ac94b67ce976988c4138035677563d169678e3e9a9b65a5296",
          "linkedWithoutMetadata": "8b67aac568cf73ac94b67ce976988c4138035677563d169678e3e9a9b65a5296"
        },
        "inherit": [],
        "libraries": [],
        "methods": [
          "()",
          "registerOfficer(address,string,string)",
          "deregisterOfficer(address)",
          "isOfficerRegistered(address)",
          "logViolation(string,uint256,string,address)",
          "getViolation(bytes32)",
          "getVehicleViolations(string)",
          "getVehicleViolationCount(string)",
          "payFine(bytes32)",
          "getTotalFinesPaid()",
          "submitAppeal(bytes32,string)",
          "getAppeal(bytes32)",
          "resolveAppeal(bytes32,bool,string)",
          "getTotalViolations()",
          "getContractBalance()",
          "withdrawFunds(uint256)",
          "()",
          "()"
        ],
        "linkReferences": [],
        "errors": [
          {
            "kind": "constructor",
            "contract": "TrafficEnforcement",
            "src": "contracts/TrafficEnforcement.sol:114"
          }
        ],
        "layout": {
          "storage": [
            {
              "label": "admin",
              "offset": 0,
              "slot": "0",
              "type": "t_address",
              "contract": "TrafficEnforcement",
              "src": "contracts/TrafficEnforcement.sol:66"
            },
            {
              "label": "violations",
              "offset": 0,
              "slot": "1",
              "type": "t_mapping(t_bytes32,t_struct(Violation)2057_storage)",
              "contract": "TrafficEnforcement",
              "src": "contracts/TrafficEnforcement.sol:68"
            },
            {
              "label": "officers",
              "offset": 0,
              "slot": "2",
              "type": "t_mapping(t_address,t_struct(Officer)2069_storage)",
              "contract": "TrafficEnforcement",
              "src": "contracts/TrafficEnforcement.sol:69"
            },
            {
              "label": "vehicleViolations",
              "offset": 0,
              "slot": "3",
              "type": "t_mapping(t_string_memory_ptr,t_array(t_bytes32)dyn_storage)",
              "contract": "TrafficEnforcement",
              "src": "contracts/TrafficEnforcement.sol:70"
            },
            {
              "label": "appeals",
              "offset": 0,
              "slot": "4",
              "type": "t_mapping(t_bytes32,t_struct(Appeal)2085_storage)",
              "contract": "TrafficEnforcement",
              "src": "contracts/TrafficEnforcement.sol:71"
            },
            {
              "label": "totalViolations",
              "offset": 0,
              "slot": "5",
              "type": "t_uint256",
              "contract": "TrafficEnforcement",
              "src": "contracts/TrafficEnforcement.sol:73"
            },
            {
              "label": "totalFinesPaid",
              "offset": 0,
              "slot": "6",
              "type": "t_uint256",
              "contract": "TrafficEnforcement",
              "src": "contracts/TrafficEnforcement.sol:74"
            },
            {
              "label": "offenseFines",
              "offset": 0,
              "slot": "7",
              "type": "t_mapping(t_uint256,t_uint256)",
              "contract": "TrafficEnforcement",
              "src": "contracts/TrafficEnforcement.sol:77"
            },
            {
              "label": "offenseNames",
              "offset": 0,
              "slot": "8",
              "type": "t_mapping(t_uint256,t_string_storage)",
              "contract": "TrafficEnforcement",
              "src": "contracts/TrafficEnforcement.sol:78"
            }
          ],
          "types": {
            "t_address": {
              "label": "address",
              "numberOfBytes": "20"
            },
            "t_array(t_bytes32)dyn_storage": {
              "label": "bytes32[]",
              "numberOfBytes": "32"
            },
            "t_bool": {
              "label": "bool",
              "numberOfBytes": "1"
            },
            "t_bytes32": {
              "label": "bytes32",
              "numberOfBytes": "32"
            },
            "t_enum(ViolationStatus)2034": {
              "label": "enum TrafficEnforcement.ViolationStatus",
              "members": [
                "Unpaid",
                "Paid",
                "Appealed",
                "Waived",
                "Rejected"
              ],
              "numberOfBytes": "1"
            },
            "t_mapping(t_address,t_struct(Officer)2069_storage)": {
              "label": "mapping(address => struct TrafficEnforcement.Officer)",
              "numberOfBytes": "32"
            },
            "t_mapping(t_bytes32,t_struct(Appeal)2085_storage)": {
              "label": "mapping(bytes32 => struct TrafficEnforcement.Appeal)",
              "numberOfBytes": "32"
            },
            "t_mapping(t_bytes32,t_struct(Violation)2057_storage)": {
              "label": "mapping(bytes32 => struct TrafficEnforcement.Violation)",
              "numberOfBytes": "32"
            },
            "t_mapping(t_string_memory_ptr,t_array(t_bytes32)dyn_storage)": {
              "label": "mapping(string => bytes32[])",
              "numberOfBytes": "32"
            },
            "t_mapping(t_uint256,t_string_storage)": {
              "label": "mapping(uint256 => string)",
              "numberOfBytes": "32"
            },
            "t_mapping(t_uint256,t_uint256)": {
              "label": "mapping(uint256 => uint256)",
              "numberOfBytes": "32"
            },
            "t_string_memory_ptr": {
              "label": "string",
              "numberOfBytes": "32"
            },
            "t_string_storage": {
              "label": "string",
              "numberOfBytes": "32"
            },
            "t_struct(Appeal)2085_storage": {
              "label": "struct TrafficEnforcement.Appeal",
              "members": [
                {
                  "label": "violationId",
                  "type": "t_bytes32",
                  "offset": 0,
                  "slot": "0"
                },
                {
                  "label": "driverId",
                  "type": "t_address",
                  "offset": 0,
                  "slot": "1"
                },
                {
                  "label": "appealReason",
                  "type": "t_string_storage",
                  "offset": 0,
                  "slot": "2"
                },
                {
                  "label": "appealTime",
                  "type": "t_uint256",
                  "offset": 0,
                  "slot": "3"
                },
                {
                  "label": "resolved",
                  "type": "t_bool",
                  "offset": 0,
                  "slot": "4"
                },
                {
                  "label": "waived",
                  "type": "t_bool",
                  "offset": 1,
                  "slot": "4"
                },
                {
                  "label": "judgeNotes",
                  "type": "t_string_storage",
                  "offset": 0,
                  "slot": "5"
                }
              ],
              "numberOfBytes": "192"
            },
            "t_struct(Officer)2069_storage": {
              "label": "struct TrafficEnforcement.Officer",
              "members": [
                {
                  "label": "officerId",
                  "type": "t_address",
                  "offset": 0,
                  "slot": "0"
                },
                {
                  "label": "name",
                  "type": "t_string_storage",
                  "offset": 0,
                  "slot": "1"
                },
                {
                  "label": "badgeNumber",
                  "type": "t_string_storage",
                  "offset": 0,
                  "slot": "2"
                },
                {
                  "label": "isRegistered",
                  "type": "t_bool",
                  "offset": 0,
                  "slot": "3"
                },
                {
                  "label": "registrationTime",
                  "type": "t_uint256",
                  "offset": 0,
                  "slot": "4"
                }
              ],
              "numberOfBytes": "160"
            },
            "t_struct(Violation)2057_storage": {
              "label": "struct TrafficEnforcement.Violation",
              "members": [
                {
                  "label": "violationId",
                  "type": "t_bytes32",
                  "offset": 0,
                  "slot": "0"
                },
                {
                  "label": "vehicleId",
                  "type": "t_string_storage",
                  "offset": 0,
                  "slot": "1"
                },
                {
                  "label": "officerId",
                  "type": "t_address",
                  "offset": 0,
                  "slot": "2"
                },
                {
                  "label": "offenseCode",
                  "type": "t_uint256",
                  "offset": 0,
                  "slot": "3"
                },
                {
                  "label": "evidenceHash",
                  "type": "t_string_storage",
                  "offset": 0,
                  "slot": "4"
                },
                {
                  "label": "timestamp",
                  "type": "t_uint256",
                  "offset": 0,
                  "slot": "5"
                },
                {
                  "label": "fineAmount",
                  "type": "t_uint256",
                  "offset": 0,
                  "slot": "6"
                },
                {
                  "label": "status",
                  "type": "t_enum(ViolationStatus)2034",
                  "offset": 0,
                  "slot": "7"
                },
                {
                  "label": "driverId",
                  "type": "t_address",
                  "offset": 1,
                  "slot": "7"
                },
                {
                  "label": "offenseName",
                  "type": "t_string_storage",
                  "offset": 0,
                  "slot": "8"
                }
              ],
              "numberOfBytes": "288"
            },
            "t_uint256": {
              "label": "uint256",
              "numberOfBytes": "32"
            }
          },
          "layoutVersion": "1.2",
          "flat": true,
          "namespaces": {}
        },
        "solcVersion": "0.8.22"
      },
      "contracts/TrafficEnforcementV2.sol:TrafficEnforcementV2": {
        "src": "contracts/TrafficEnforcementV2.sol:26",
        "version": {
          "withMetadata": "a624cb4579873bae8ab9ac5b4b8919195a528f4fdf1785069d9d93e7a790b0f3",
          "withoutMetadata": "2a2beadb7e0788e53143049f7e8cb15642cde103afbf56a2c42c41859cffd10d",
          "linkedWithoutMetadata": "2a2beadb7e0788e53143049f7e8cb15642cde103afbf56a2c42c41859cffd10d"
        },
        "inherit": [
          "@openzeppelin/contracts-upgradeable/proxy/utils/UUPSUpgradeable.sol:UUPSUpgradeable",
          "@openzeppelin/contracts/interfaces/draft-IERC1822.sol:IERC1822Proxiable",
          "@openzeppelin/contracts-upgradeable/utils/ReentrancyGuardUpgradeable.sol:ReentrancyGuardUpgradeable",
          "@openzeppelin/contracts-upgradeable/utils/PausableUpgradeable.sol:PausableUpgradeable",
          "@openzeppelin/contracts-upgradeable/access/AccessControlUpgradeable.sol:AccessControlUpgradeable",
          "@openzeppelin/contracts-upgradeable/utils/introspection/ERC165Upgradeable.sol:ERC165Upgradeable",
          "@openzeppelin/contracts/utils/introspection/IERC165.sol:IERC165",
          "@openzeppelin/contracts/access/IAccessControl.sol:IAccessControl",
          "@openzeppelin/contracts-upgradeable/utils/ContextUpgradeable.sol:ContextUpgradeable",
          "@openzeppelin/contracts-upgradeable/proxy/utils/Initializable.sol:Initializable"
        ],
        "libraries": [],
        "methods": [
          "initialize(address)",
          "registerOfficer(address,string,string)",
          "deactivateOfficer(address)",
          "isOfficerActive(address)",
          "logViolation(string,uint32,string,address)",
          "getViolation(bytes32)",
          "getVehicleViolations(string,uint256,uint256)",
          "payFine(bytes32)",
          "submitAppeal(bytes32,string)",
          "resolveAppeal(bytes32,bool,string)",
          "claimRefund()",
          "updateOffense(uint32,uint256,string,bool)",
          "withdrawFunds(address,uint256)",
          "pause()",
          "unpause()",
          "()",
          "()"
        ],
        "linkReferences": [],
        "errors": [],
        "layout": {
          "storage": [
            {
              "label": "violations",
              "offset": 0,
              "slot": "0",
              "type": "t_mapping(t_bytes32,t_struct(Violation)3137_storage)",
              "contract": "TrafficEnforcementV2",
              "src": "contracts/TrafficEnforcementV2.sol:149"
            },
            {
              "label": "officers",
              "offset": 0,
              "slot": "1",
              "type": "t_mapping(t_address,t_struct(Officer)3153_storage)",
              "contract": "TrafficEnforcementV2",
              "src": "contracts/TrafficEnforcementV2.sol:150"
            },
            {
              "label": "vehicleViolations",
              "offset": 0,
              "slot": "2",
              "type": "t_mapping(t_string_memory_ptr,t_array(t_bytes32)dyn_storage)",
              "contract": "TrafficEnforcementV2",
              "src": "contracts/TrafficEnforcementV2.sol:151"
            },
            {
              "label": "appeals",
              "offset": 0,
              "slot": "3",
              "type": "t_mapping(t_bytes32,t_struct(Appeal)3175_storage)",
              "contract": "TrafficEnforcementV2",
              "src": "contracts/TrafficEnforcementV2.sol:152"
            },
            {
              "label": "offenses",
              "offset": 0,
              "slot": "4",
              "type": "t_mapping(t_uint32,t_struct(Offense)3183_storage)",
              "contract": "TrafficEnforcementV2",
              "src": "contracts/TrafficEnforcementV2.sol:153"
            },
            {
              "label": "totalViolations",
              "offset": 0,
              "slot": "5",
              "type": "t_uint256",
              "contract": "TrafficEnforcementV2",
              "src": "contracts/TrafficEnforcementV2.sol:158"
            },
            {
              "label": "totalFinesPaid",
              "offset": 0,
              "slot": "6",
              "type": "t_uint256",
              "contract": "TrafficEnforcementV2",
              "src": "contracts/TrafficEnforcementV2.sol:159"
            },
            {
              "label": "totalFinesRefunded",
              "offset": 0,
              "slot": "7",
              "type": "t_uint256",
              "contract": "TrafficEnforcementV2",
              "src": "contracts/TrafficEnforcementV2.sol:160"
            },
            {
              "label": "officerDailyViolations",
              "offset": 0,
              "slot": "8",
              "type": "t_mapping(t_address,t_mapping(t_uint256,t_uint256))",
              "contract": "TrafficEnforcementV2",
              "src": "contracts/TrafficEnforcementV2.sol:165"
            },
            {
              "label": "pendingRefunds",
              "offset": 0,
              "slot": "9",
              "type": "t_mapping(t_address,t_uint256)",
              "contract": "TrafficEnforcementV2",
              "src": "contracts/TrafficEnforcementV2.sol:170"
            },
            {
              "label": "version",
              "offset": 0,
              "slot": "10",
              "type": "t_uint256",
              "contract": "TrafficEnforcementV2",
              "src": "contracts/TrafficEnforcementV2.sol:175"
            }
          ],
          "types": {
            "t_address": {
              "label": "address",
              "numberOfBytes": "20"
            },
            "t_array(t_bytes32)dyn_storage": {
              "label": "bytes32[]",
              "numberOfBytes": "32"
            },
            "t_bool": {
              "label": "bool",
              "numberOfBytes": "1"
            },
            "t_bytes32": {
              "label": "bytes32",
              "numberOfBytes": "32"
            },
            "t_enum(ViolationStatus)3112": {
              "label": "enum TrafficEnforcementV2.ViolationStatus",
              "members": [
                "Unpaid",
                "Paid",
                "Appealed",
                "Waived",
                "Rejected",
                "Refunded"
              ],
              "numberOfBytes": "1"
            },
            "t_mapping(t_address,t_mapping(t_uint256,t_uint256))": {
              "label": "mapping(address => mapping(uint256 => uint256))",
              "numberOfBytes": "32"
            },
            "t_mapping(t_address,t_struct(Officer)3153_storage)": {
              "label": "mapping(address => struct TrafficEnforcementV2.Officer)",
              "numberOfBytes": "32"
            },
            "t_mapping(t_address,t_uint256)": {
              "label": "mapping(address => uint256)",
              "numberOfBytes": "32"
            },
            "t_mapping(t_bytes32,t_struct(Appeal)3175_storage)": {
              "label": "mapping(bytes32 => struct TrafficEnforcementV2.Appeal)",
              "numberOfBytes": "32"
            },
            "t_mapping(t_bytes32,t_struct(Violation)3137_storage)": {
              "label": "mapping(bytes32 => struct TrafficEnforcementV2.Violation)",
              "numberOfBytes": "32"
            },
            "t_mapping(t_string_memory_ptr,t_array(t_bytes32)dyn_storage)": {
              "label": "mapping(string => bytes32[])",
              "numberOfBytes": "32"
            },
            "t_mapping(t_uint256,t_uint256)": {
              "label": "mapping(uint256 => uint256)",
              "numberOfBytes": "32"
            },
            "t_mapping(t_uint32,t_struct(Offense)3183_storage)": {
              "label": "mapping(uint32 => struct TrafficEnforcementV2.Offense)",
              "numberOfBytes": "32"
            },
            "t_string_memory_ptr": {
              "label": "string",
              "numberOfBytes": "32"
            },
            "t_string_storage": {
              "label": "string",
              "numberOfBytes": "32"
            },
            "t_struct(Appeal)3175_storage": {
              "label": "struct TrafficEnforcementV2.Appeal",
              "members": [
                {
                  "label": "violationId",
                  "type": "t_bytes32",
                  "offset": 0,
                  "slot": "0"
                },
                {
                  "label": "appellant",
                  "type": "t_address",
                  "offset": 0,
                  "slot": "1"
                },
                {
                  "label": "appealReason",
                  "type": "t_string_storage",
                  "offset": 0,
                  "slot": "2"
                },
                {
                  "label": "appealTime",
                  "type": "t_uint256",
                  "offset": 0,
                  "slot": "3"
                },
                {
                  "label": "resolved",
                  "type": "t_bool",
                  "offset": 0,
                  "slot": "4"
                },
                {
                  "label": "approved",
                  "type": "t_bool",
                  "offset": 1,
                  "slot": "4"
                },
                {
                  "label": "resolution",
                  "type": "t_string_storage",
                  "offset": 0,
                  "slot": "5"
                },
                {
                  "label": "resolvedBy",
                  "type": "t_address",
                  "offset": 0,
                  "slot": "6"
                },
                {
                  "label": "appealCount",
                  "type": "t_uint256",
                  "offset": 0,
                  "slot": "7"
                },
                {
                  "label": "lastAppealTime",
                  "type": "t_uint256",
                  "offset": 0,
                  "slot": "8"
                }
              ],
              "numberOfBytes": "288"
            },
            "t_struct(Offense)3183_storage": {
              "label": "struct TrafficEnforcementV2.Offense",
              "members": [
                {
                  "label": "fineAmountKES",
                  "type": "t_uint256",
                  "offset": 0,
                  "slot": "0"
                },
                {
                  "label": "name",
                  "type": "t_string_storage",
                  "offset": 0,
                  "slot": "1"
                },
                {
                  "label": "isActive",
                  "type": "t_bool",
                  "offset": 0,
                  "slot": "2"
                }
              ],
              "numberOfBytes": "96"
            },
            "t_struct(Officer)3153_storage": {
              "label": "struct TrafficEnforcementV2.Officer",
              "members": [
                {
                  "label": "officerId",
                  "type": "t_address",
                  "offset": 0,
                  "slot": "0"
                },
                {
                  "label": "name",
                  "type": "t_string_storage",
                  "offset": 0,
                  "slot": "1"
                },
                {
                  "label": "badgeNumber",
                  "type": "t_string_storage",
                  "offset": 0,
                  "slot": "2"
                },
                {
                  "label": "isActive",
                  "type": "t_bool",
                  "offset": 0,
                  "slot": "3"
                },
                {
                  "label": "registrationTime",
                  "type": "t_uint256",
                  "offset": 0,
                  "slot": "4"
                },
                {
                  "label": "dailyViolationCount",
                  "type": "t_uint256",
                  "offset": 0,
                  "slot": "5"
                },
                {
                  "label": "lastViolationDate",
                  "type": "t_uint256",
                  "offset": 0,
                  "slot": "6"
                }
              ],
              "numberOfBytes": "224"
            },
            "t_struct(Violation)3137_storage": {
              "label": "struct TrafficEnforcementV2.Violation",
              "members": [
                {
                  "label": "violationId",
                  "type": "t_bytes32",
                  "offset": 0,
                  "slot": "0"
                },
                {
                  "label": "vehicleId",
                  "type": "t_string_storage",
                  "offset": 0,
                  "slot": "1"
                },
                {
                  "label": "officerId",
                  "type": "t_address",
                  "offset": 0,
                  "slot": "2"
                },
                {
                  "label": "offenseCode",
                  "type": "t_uint32",
                  "offset": 20,
                  "slot": "2"
                },
                {
                  "label": "evidenceHash",
                  "type": "t_string_storage",
                  "offset": 0,
                  "slot": "3"
                },
                {
                  "label": "timestamp",
                  "type": "t_uint256",
                  "offset": 0,
                  "slot": "4"
                },
                {
                  "label": "fineAmount",
                  "type": "t_uint256",
                  "offset": 0,
                  "slot": "5"
                },
                {
                  "label": "status",
                  "type": "t_enum(ViolationStatus)3112",
                  "offset": 0,
                  "slot": "6"
                },
                {
                  "label": "driverId",
                  "type": "t_address",
                  "offset": 1,
                  "slot": "6"
                },
                {
                  "label": "paidAmount",
                  "type": "t_uint256",
                  "offset": 0,
                  "slot": "7"
                },
                {
                  "label": "paidBy",
                  "type": "t_address",
                  "offset": 0,
                  "slot": "8"
                }
              ],
              "numberOfBytes": "288"
            },
            "t_uint256": {
              "label": "uint256",
              "numberOfBytes": "32"
            },
            "t_uint32": {
              "label": "uint32",
              "numberOfBytes": "4"
            },
            "t_mapping(t_bytes32,t_struct(RoleData)27_storage)": {
              "label": "mapping(bytes32 => struct AccessControlUpgradeable.RoleData)"
            },
            "t_struct(RoleData)27_storage": {
              "label": "struct AccessControlUpgradeable.RoleData",
              "members": [
                {
                  "label": "hasRole",
                  "type": "t_mapping(t_address,t_bool)"
                },
                {
                  "label": "adminRole",
                  "type": "t_bytes32"
                }
              ]
            },
            "t_mapping(t_address,t_bool)": {
              "label": "mapping(address => bool)"
            },
            "t_uint64": {
              "label": "uint64"
            }
          },
          "layoutVersion": "1.2",
          "flat": true,
          "namespaces": {
            "erc7201:openzeppelin.storage.ReentrancyGuard": [
              {
                "contract": "ReentrancyGuardUpgradeable",
                "label": "_status",
                "type": "t_uint256",
                "src": "@openzeppelin/contracts-upgradeable/utils/ReentrancyGuardUpgradeable.sol:43"
              }
            ],
            "erc7201:openzeppelin.storage.Pausable": [
              {
                "contract": "PausableUpgradeable",
                "label": "_paused",
                "type": "t_bool",
                "src": "@openzeppelin/contracts-upgradeable/utils/PausableUpgradeable.sol:21"
              }
            ],
            "erc7201:openzeppelin.storage.AccessControl": [
              {
                "contract": "AccessControlUpgradeable",
                "label": "_roles",
                "type": "t_mapping(t_bytes32,t_struct(RoleData)27_storage)",
                "src": "@openzeppelin/contracts-upgradeable/access/AccessControlUpgradeable.sol:62"
              }
            ],
            "erc7201:openzeppelin.storage.Initializable": [
              {
                "contract": "Initializable",
                "label": "_initialized",
                "type": "t_uint64",
                "src": "@openzeppelin/contracts-upgradeable/proxy/utils/Initializable.sol:69"
              },
              {
                "contract": "Initializable",
                "label": "_initializing",
                "type": "t_bool",
                "src": "@openzeppelin/contracts-upgradeable/proxy/utils/Initializable.sol:73"
              }
            ]
          }
        },
        "solcVersion": "0.8.22"
      }
    }
  ]
}